text_algorithms/__init__.py
Text_Algorithms-0.1.dist-info/LICENSE.txt
Text_Algorithms-0.1.dist-info/METADATA
Text_Algorithms-0.1.dist-info/WHEEL
Text_Algorithms-0.1.dist-info/top_level.txt
Text_Algorithms-0.1.dist-info/RECORD
