Metadata-Version: 2.1
Name: Text-Algorithms
Version: 0.1
Summary: Implementation of the algorithms from the book: 'Text Algorithms' by Maxime Crochemore and Wojciech Rytter.
Home-page: UNKNOWN
Author: Lambros Kaplanis
Author-email: lambroskap@hotmail.com
License: UNKNOWN
Platform: UNKNOWN
Classifier: Programming Language :: Python :: 3
Classifier: License :: OSI Approved :: MIT License
Classifier: Operating System :: OS Independent
License-File: LICENSE.txt
